matrix_alertbot/__init__.py
matrix_alertbot/_version.py
matrix_alertbot/alert.py
matrix_alertbot/alertmanager.py
matrix_alertbot/callback.py
matrix_alertbot/chat_functions.py
matrix_alertbot/command.py
matrix_alertbot/config.py
matrix_alertbot/errors.py
matrix_alertbot/main.py
matrix_alertbot/matrix.py
matrix_alertbot/webhook.py
matrix_alertbot/resources/templates/alert.html.j2
matrix_alertbot/resources/templates/alert.txt.j2
tests/__init__.py
tests/test_alert.py
tests/test_alertmanager.py
tests/test_callback.py
tests/test_chat_functions.py
tests/test_command.py
tests/test_config.py
tests/test_matrix.py
tests/test_webhook.py
tests/resources/config/config.full.yml
tests/resources/config/config.minimal.yml
tests/resources/templates/alert.html.j2
tests/resources/templates/alert.txt.j2
matrix_alertbot-0.3.3.dist-info/LICENSE
matrix_alertbot-0.3.3.dist-info/METADATA
matrix_alertbot-0.3.3.dist-info/WHEEL
matrix_alertbot-0.3.3.dist-info/entry_points.txt
matrix_alertbot-0.3.3.dist-info/top_level.txt
matrix_alertbot-0.3.3.dist-info/RECORD
