Metadata-Version: 2.1
Name: matrix-alertbot
Version: 0.3.3
Summary: A matrix bot to manage alerts from Alertmanager
Home-page: https://gitlab.domainepublic.net/Neutrinet/matrix-alertbot
Project-URL: Documentation, https://gitlab.domainepublic.net/Neutrinet/matrix-alertbot/-/blob/master/README.md
Project-URL: Source, https://gitlab.domainepublic.net/Neutrinet/matrix-alertbot
Project-URL: Tracker, https://gitlab.domainepublic.net/Neutrinet/matrix-alertbot/-/issues
Classifier: License :: OSI Approved :: GNU Affero General Public License v3 or later (AGPLv3+)
Classifier: Programming Language :: Python :: 3 :: Only
Classifier: Programming Language :: Python :: 3.10
Classifier: Programming Language :: Python :: 3.11
Classifier: Programming Language :: Python :: 3.12
Requires-Python: >=3.9
License-File: LICENSE
Requires-Dist: aiohttp >=3.8.1
Requires-Dist: aiohttp-prometheus-exporter >=0.2.4
Requires-Dist: aiotools >=1.5.9
Requires-Dist: diskcache >=5.4.0
Requires-Dist: jinja2 >=3.1.2
Requires-Dist: matrix-nio >=0.24.0
Requires-Dist: Markdown >=3.3.7
Requires-Dist: pytimeparse2 >=1.4.0
Requires-Dist: PyYAML >=5.4.1
Requires-Dist: typing-extensions >=4.3.0
Provides-Extra: all
Requires-Dist: coverage >=6.4.1 ; extra == 'all'
Requires-Dist: black >=22.6.0 ; extra == 'all'
Requires-Dist: flake8 >=4.0.1 ; extra == 'all'
Requires-Dist: flake8-comprehensions >=3.10.0 ; extra == 'all'
Requires-Dist: isort >=5.10.1 ; extra == 'all'
Requires-Dist: mypy >=0.961 ; extra == 'all'
Requires-Dist: pytest >=7.4.0 ; extra == 'all'
Requires-Dist: pytest-cov >=4.1.0 ; extra == 'all'
Requires-Dist: pytest-asyncio >=0.18.3 ; extra == 'all'
Requires-Dist: freezegun >=1.2.1 ; extra == 'all'
Requires-Dist: types-PyYAML >=6.0.9 ; extra == 'all'
Requires-Dist: types-setuptools >=62.6.0 ; extra == 'all'
Requires-Dist: matrix-nio[e2e] >=0.24.0 ; extra == 'all'
Provides-Extra: e2e
Requires-Dist: matrix-nio[e2e] >=0.24.0 ; extra == 'e2e'
Provides-Extra: test
Requires-Dist: coverage >=6.4.1 ; extra == 'test'
Requires-Dist: black >=22.6.0 ; extra == 'test'
Requires-Dist: flake8 >=4.0.1 ; extra == 'test'
Requires-Dist: flake8-comprehensions >=3.10.0 ; extra == 'test'
Requires-Dist: isort >=5.10.1 ; extra == 'test'
Requires-Dist: mypy >=0.961 ; extra == 'test'
Requires-Dist: pytest >=7.4.0 ; extra == 'test'
Requires-Dist: pytest-cov >=4.1.0 ; extra == 'test'
Requires-Dist: pytest-asyncio >=0.18.3 ; extra == 'test'
Requires-Dist: freezegun >=1.2.1 ; extra == 'test'
Requires-Dist: types-PyYAML >=6.0.9 ; extra == 'test'
Requires-Dist: types-setuptools >=62.6.0 ; extra == 'test'
